vortezwohl/__init__.py
vortezwohl/cache/__init__.py
vortezwohl/cache/base_cache.py
vortezwohl/cache/lru_cache.py
vortezwohl/concurrent/__init__.py
vortezwohl/concurrent/future_result.py
vortezwohl/concurrent/lock.py
vortezwohl/concurrent/thread_pool.py
vortezwohl/crypt/__init__.py
vortezwohl/crypt/hash.py
vortezwohl/func/__init__.py
vortezwohl/func/retry.py
vortezwohl/func/timeout.py
vortezwohl/io/__init__.py
vortezwohl/io/file.py
vortezwohl/io/http_client.py
vortezwohl/iter/__init__.py
vortezwohl/iter/iter.py
vortezwohl/nlp/__init__.py
vortezwohl/nlp/base_string_similarity.py
vortezwohl/nlp/levenshtein_distance.py
vortezwohl/nlp/longest_common_substring.py
vortezwohl/random/__init__.py
vortezwohl/random/seed_generator.py
vortezwohl/sys/__init__.py
vortezwohl/sys/system.py
vortezwohl-0.1.0.dist-info/licenses/LICENSE
vortezwohl-0.1.0.dist-info/METADATA
vortezwohl-0.1.0.dist-info/WHEEL
vortezwohl-0.1.0.dist-info/top_level.txt
vortezwohl-0.1.0.dist-info/RECORD
