Metadata-Version: 2.4
Name: vortezwohl
Version: 0.1.0
Summary: Practical SDKs by vortezwohl.
Requires-Python: >=3.10
License-File: LICENSE
Requires-Dist: overrides
Requires-Dist: psutil
Requires-Dist: requests
Requires-Dist: typing-extensions
Requires-Dist: urllib3>=2.5.0
Dynamic: license-file
